{
    "1709": {
        "KB4043961": {
            "heading": "October 17, 2017&#x2014;KB4043961 (OS Build 16299.19)",
            "releaseDate": "2017-10-17",
            "releaseVersion": "16299.19",
            "updateUrl": "https://support.microsoft.com/help/4043961"
        },
        "KB4048955": {
            "heading": "November 14, 2017&#x2014;KB4048955 (OS Build 16299.64)",
            "releaseDate": "2017-11-14",
            "releaseVersion": "16299.64",
            "updateUrl": "https://support.microsoft.com/help/4048955"
        },
        "KB4051963": {
            "heading": "November 30, 2017&#x2014;KB4051963 (OS Build 16299.98)",
            "releaseDate": "2017-11-30",
            "releaseVersion": "16299.98",
            "updateUrl": "https://support.microsoft.com/help/4051963"
        }
    }
}